msdataviewer/__init__.py
msdataviewer/__main__.py
msdataviewer-1.0.0.dist-info/METADATA
msdataviewer-1.0.0.dist-info/WHEEL
msdataviewer-1.0.0.dist-info/entry_points.txt
msdataviewer-1.0.0.dist-info/top_level.txt
msdataviewer-1.0.0.dist-info/RECORD
