Metadata-Version: 2.1
Name: msdataviewer
Version: 1.0.0
Summary: A package for handling SQT format ProLucid search files
Home-page: https://github.com/prashanthciryam/DataViewer
Author: Prashanth Ciryam
Author-email: psciryam@gmail.com
Classifier: Development Status :: 3 - Alpha
Classifier: Intended Audience :: Science/Research
Classifier: License :: OSI Approved :: MIT License
Classifier: Programming Language :: Python :: 3
Classifier: Programming Language :: Python :: 3.6
Classifier: Programming Language :: Python :: 3.7
Classifier: Programming Language :: Python :: 3.8
Classifier: Programming Language :: Python :: 3.9
Classifier: Programming Language :: Python :: 3.10
Classifier: Programming Language :: Python :: 3.11
Requires-Dist: pandas >=1.0.0
Requires-Dist: biopython >=1.78
Requires-Dist: pyteomics >=4.4
Requires-Dist: PyQt5 >=5.15
Requires-Dist: numpy >=1.18
Requires-Dist: sqtIO >=0.1.1
